odoo/addons/product_category_code/README.rst
odoo/addons/product_category_code/__init__.py
odoo/addons/product_category_code/__manifest__.py
odoo/addons/product_category_code/i18n/es_PA.po
odoo/addons/product_category_code/i18n/it.po
odoo/addons/product_category_code/i18n/product_category_code.pot
odoo/addons/product_category_code/models/__init__.py
odoo/addons/product_category_code/models/product_category.py
odoo/addons/product_category_code/readme/CONTRIBUTORS.rst
odoo/addons/product_category_code/readme/DESCRIPTION.rst
odoo/addons/product_category_code/static/description/icon.png
odoo/addons/product_category_code/static/description/index.html
odoo/addons/product_category_code/tests/__init__.py
odoo/addons/product_category_code/tests/test_category_code.py
odoo/addons/product_category_code/views/product_category.xml
odoo13_addon_product_category_code-13.0.1.0.1.dev6.dist-info/METADATA
odoo13_addon_product_category_code-13.0.1.0.1.dev6.dist-info/WHEEL
odoo13_addon_product_category_code-13.0.1.0.1.dev6.dist-info/top_level.txt
odoo13_addon_product_category_code-13.0.1.0.1.dev6.dist-info/RECORD
